attis/__init__.py
attis/main.py
attis/libcore/__init__.py
attis/libcore/action_manager.py
attis/libcore/preset_manager.py
attis/libcore/action/__init__.py
attis/libcore/action/base_action.py
attis/libcore/action/exe_action.py
attis/libcore/action/help_action.py
attis/libcore/action/list_action.py
attis/libcore/action/remove_action.py
attis/libcore/action/set_action.py
attis/libcore/action/term_style.py
attis/libcore/action/version_action.py
attis/static/config.yml
attis/static/help.yml
attis-0.0.3.post3.dist-info/LICENSE
attis-0.0.3.post3.dist-info/METADATA
attis-0.0.3.post3.dist-info/WHEEL
attis-0.0.3.post3.dist-info/entry_points.txt
attis-0.0.3.post3.dist-info/top_level.txt
attis-0.0.3.post3.dist-info/RECORD
