Metadata-Version: 2.1
Name: attis
Version: 0.0.3.post3
Summary: A productivity tool for linux terminal
Home-page: https://github.com/kyzas/attis
Download-URL: https://github.com/kyzas/attis/tarball/master
Author: kyzas
Author-email: minhng92@gmail.com
Maintainer: kyzas
Maintainer-email: minhng92@gmail.com
License: MIT
Classifier: Development Status :: 4 - Beta
Classifier: License :: OSI Approved :: MIT License
Classifier: Topic :: Software Development :: Libraries :: Python Modules
Classifier: Intended Audience :: Developers
Classifier: Programming Language :: Python :: 3
Classifier: Programming Language :: Python :: 3.5
Classifier: Programming Language :: Python :: 3.6
Classifier: Programming Language :: Python :: 3.7
Classifier: Programming Language :: Python :: 3.8
Classifier: Programming Language :: Python :: 3.9
Classifier: Programming Language :: Python :: 3.10
Classifier: Programming Language :: Python :: Implementation
Requires-Python: <4,>=3.5
License-File: LICENSE
Requires-Dist: plazy >=0.1.6
Requires-Dist: scake >=0.3.2
Requires-Dist: prettytable
Requires-Dist: omegaconf
